Exodushcate.py
exodushcate-1.7.2.dist-info/LICENSE
exodushcate-1.7.2.dist-info/METADATA
exodushcate-1.7.2.dist-info/WHEEL
exodushcate-1.7.2.dist-info/RECORD
