Metadata-Version: 2.1
Name: Exodushcate
Version: 1.7.2
Summary: Convertor .seco file from Exodus Wallet, seco to hashcat string
License: MIT
Keywords: egg,bacon,sausage,tomatoes,Lobster Thermidor
Author: Isaac Florentine
Requires-Python: >=3.7,<4.0
Classifier: License :: OSI Approved :: MIT License
Classifier: Programming Language :: Python :: 3
Classifier: Programming Language :: Python :: 3.7
Classifier: Programming Language :: Python :: 3.8
Classifier: Programming Language :: Python :: 3.9
Classifier: Programming Language :: Python :: 3.10
Classifier: Programming Language :: Python :: 3.11
Classifier: Programming Language :: Python :: 3.12
